s_tui/__init__.py
s_tui/about_menu.py
s_tui/help_menu.py
s_tui/helper_functions.py
s_tui/s_tui.py
s_tui/sensors_menu.py
s_tui/stress_menu.py
s_tui/sources/__init__.py
s_tui/sources/fan_source.py
s_tui/sources/freq_source.py
s_tui/sources/hook.py
s_tui/sources/hook_script.py
s_tui/sources/rapl_power_source.py
s_tui/sources/rapl_read.py
s_tui/sources/script_hook_loader.py
s_tui/sources/source.py
s_tui/sources/temp_source.py
s_tui/sources/util_source.py
s_tui/sturwid/__init__.py
s_tui/sturwid/bar_graph_vector.py
s_tui/sturwid/complex_bar_graph.py
s_tui/sturwid/summary_text_list.py
s_tui/sturwid/ui_elements.py
s_tui-1.0.0.dist-info/LICENSE
s_tui-1.0.0.dist-info/METADATA
s_tui-1.0.0.dist-info/WHEEL
s_tui-1.0.0.dist-info/entry_points.txt
s_tui-1.0.0.dist-info/top_level.txt
s_tui-1.0.0.dist-info/RECORD
