Metadata-Version: 2.1
Name: s-tui
Version: 1.0.0
Summary: Stress Terminal UI stress test and monitoring tool
Home-page: https://github.com/amanusk/s-tui
Author: Alex Manuskin
Author-email: amanusk@tuta.io
License: GPLv2
Keywords: stress,monitoring,TUI
Platform: UNKNOWN
Classifier: License :: OSI Approved :: GNU General Public License v2 (GPLv2)
Classifier: Operating System :: POSIX :: Linux
Classifier: Programming Language :: Python :: 2
Classifier: Programming Language :: Python :: 3
Classifier: Topic :: System :: Monitoring
Requires-Dist: psutil (>=5.6.0)
Requires-Dist: urwid (>=2.0.1)
